ziyang/__init__.py
ziyang/__main__.py
ziyang/benchmark.py
ziyang/cli.py
ziyang/core.py
ziyang/math_core.py
ziyang/optimization.py
ziyang/utils.py
ziyang/visualization.py
ziyang_sdk-3.0.0.dist-info/METADATA
ziyang_sdk-3.0.0.dist-info/WHEEL
ziyang_sdk-3.0.0.dist-info/entry_points.txt
ziyang_sdk-3.0.0.dist-info/top_level.txt
ziyang_sdk-3.0.0.dist-info/RECORD
