Metadata-Version: 2.4
Name: ziyang-sdk
Version: 3.0.0
Summary: 紫阳智库v3算力测试SDK
Author: 紫阳智库团队
Requires-Python: >=3.8
Requires-Dist: numpy>=1.21.0
Requires-Dist: pandas>=1.3.0
Requires-Dist: matplotlib>=3.5.0
Dynamic: author
Dynamic: description
Dynamic: description-content-type
Dynamic: requires-dist
Dynamic: requires-python
Dynamic: summary
